aposteriori/__init__.py
aposteriori/config.py
aposteriori/data_prep/__init__.py
aposteriori/data_prep/cli.py
aposteriori/data_prep/create_frame_data_set.py
aposteriori-2.4.0.dist-info/LICENSE
aposteriori-2.4.0.dist-info/METADATA
aposteriori-2.4.0.dist-info/WHEEL
aposteriori-2.4.0.dist-info/entry_points.txt
aposteriori-2.4.0.dist-info/top_level.txt
aposteriori-2.4.0.dist-info/RECORD
