Metadata-Version: 2.1
Name: aposteriori
Version: 2.4.0
Summary: A library for the voxelization of protein structures for protein design.
Home-page: https://github.com/wells-wood-research/aposteriori
Author: Wells Wood Research Group
Author-email: chris.wood@ed.ac.uk
Classifier: Programming Language :: Python :: 3
Classifier: License :: OSI Approved :: MIT License
Classifier: Operating System :: OS Independent
Requires-Python: >=3.8
License-File: LICENSE
Requires-Dist: ampal ==1.5.1
Requires-Dist: click ==8.1.7
Requires-Dist: h5py ==3.8.0
Requires-Dist: numpy
Requires-Dist: flake8
